fastabf/.pytest_cache/.gitignore
fastabf/.pytest_cache/CACHEDIR.TAG
fastabf/.pytest_cache/README.md
fastabf/.pytest_cache/v/cache/lastfailed
fastabf/.pytest_cache/v/cache/nodeids
fastabf/.pytest_cache/v/cache/stepwise
fastabf/DAL/__init__.py
fastabf/DAL/admitted_acute_helper.py
fastabf/DAL/dal_admitted_acute.py
fastabf/DAL/dal_admitted_subandnon_acute.py
fastabf/DAL/dal_emergency.py
fastabf/DAL/dal_nonadmitted.py
fastabf/DAL/dal_private_patient_adj.py
fastabf/HACpackage/hac_helper.py
fastabf/HACpackage/hac_processor.py
fastabf/Helpers/__init__.py
fastabf/Helpers/charlson_class.py
fastabf/Helpers/helper_remoteness_mappings.py
fastabf/__init__.py
fastabf/adjustment_mapper.py
fastabf/csvstores/__init__.py
fastabf/csvstores/admitted_acute_data.csv
fastabf/csvstores/admitted_subacute_data.csv
fastabf/csvstores/adrg_intervention_mapper_data.csv
fastabf/csvstores/adrg_mdc_mapper_data.csv
fastabf/csvstores/charlson_data.csv
fastabf/csvstores/emergency_department_data.csv
fastabf/csvstores/emergency_service_data.csv
fastabf/csvstores/hac_15p2data.csv
fastabf/csvstores/hac_adjustments_mapping_data.csv
fastabf/csvstores/hac_complexity_mapping_data.csv
fastabf/csvstores/hac_except15p2data.csv
fastabf/csvstores/hac_table_baseline_data.csv
fastabf/csvstores/mdc_factor_data.csv
fastabf/csvstores/nonadmitted_data.csv
fastabf/csvstores/postcode_to_ra16mapper.csv
fastabf/csvstores/private_acc_data.csv
fastabf/csvstores/private_service_data.csv
fastabf/csvstores/sa2_to_ra16mapper.csv
fastabf/datatypes.py
fastabf/pipelines/__init__.py
fastabf/pipelines/nwau_admitted_acute.py
fastabf/pipelines/nwau_admitted_sub_and_non_acute.py
fastabf/pipelines/nwau_emergency.py
fastabf/pipelines/nwau_nonadmitted.py
fastabf-0.8.10.dist-info/LICENSE
fastabf-0.8.10.dist-info/WHEEL
fastabf-0.8.10.dist-info/METADATA
fastabf-0.8.10.dist-info/RECORD
