Metadata-Version: 2.1
Name: fastabf
Version: 0.8.10
Summary: A robust computation package for activity based funding calculations
Home-page: https://github.com/GreenlakeMedical/fastABF
Author: Sri Sridharan
Author-email: sri@greenlakemedical.ai
Requires-Python: >=3.7.1,<4.0.0
Classifier: Programming Language :: Python :: 3
Classifier: Programming Language :: Python :: 3.8
Classifier: Programming Language :: Python :: 3.9
Requires-Dist: pandas (>=1.2,<2.0)
Project-URL: Documentation, https://greenlakemedical.github.io/fastABF/
Project-URL: Repository, https://github.com/GreenlakeMedical/fastABF
